datazets/__init__.py
datazets/datazets.py
datazets/examples.py
datazets-1.1.2.dist-info/licenses/LICENSE
datazets-1.1.2.dist-info/METADATA
datazets-1.1.2.dist-info/WHEEL
datazets-1.1.2.dist-info/top_level.txt
datazets-1.1.2.dist-info/RECORD
