Metadata-Version: 2.4
Name: datazets
Version: 1.1.2
Summary: Datazets is a python package to import well known example data sets.
Author-email: Erdogan Taskesen <erdogant@gmail.com>
License: MIT License
Project-URL: Homepage, https://erdogant.github.io/datazets
Project-URL: Download, https://github.com/erdogant/datazets/archive/{version}.tar.gz
Keywords: Python,
Classifier: Programming Language :: Python :: 3
Classifier: License :: OSI Approved :: MIT License
Classifier: Operating System :: OS Independent
Requires-Python: >=3
License-File: LICENSE
Requires-Dist: numpy
Requires-Dist: pandas
Requires-Dist: requests
Dynamic: license-file
